{
  "key": "cloud-backup-utility",
  "name": "Cloud Backup Utility",
  "description": "Cloud Backup Unility",
  "vendor": {
    "name": "HighwayThree",
    "url": "http://www.highwaythreesolutions.com"
  },
  "links": {
    "self": "<% BASE_URL %>/files/atlassian-connect.json"
  },
  "lifecycle": {
    "installed": "/api/installed",
    "uninstalled": "/api/uninstalled"
  },
  "baseUrl": "<% BASE_URL %>",
  "authentication": {
    "type": "jwt"
  },
  "scopes": ["read", "admin"],
  "modules": {
    "generalPages": [
      {
        "url": "/index.html",
        "key": "cloud-backup-utility",
        "location": "system.top.navigation.bar",
        "name": {
          "value": "Cloud Backups"
        }
      }
    ]
  }
}
